zever_local/__init__.py
zever_local/inverter.py
zever_local-1.0.3.dist-info/LICENSE
zever_local-1.0.3.dist-info/METADATA
zever_local-1.0.3.dist-info/WHEEL
zever_local-1.0.3.dist-info/top_level.txt
zever_local-1.0.3.dist-info/RECORD
