Metadata-Version: 2.1
Name: zever-local
Version: 1.0.3
Summary: Connect locally to a Zeversolar inverter.
Home-page: https://github.com/NECH2004/zever_local
Author: NECH
License: UNKNOWN
Project-URL: Bug Tracker, https://github.com/NECH2004/zever_local/issues
Platform: UNKNOWN
Classifier: Programming Language :: Python :: 3
Classifier: License :: OSI Approved :: MIT License
Classifier: Operating System :: OS Independent
Requires-Python: >=3.6
License-File: LICENSE
